dtrc/__init__.py
dtrc/_modidx.py
dtrc/atyp.py
dtrc/cats.py
dtrc/cfgs.py
dtrc/cons.py
dtrc/data.py
dtrc/dlit.py
dtrc/dmod.py
dtrc/dset.py
dtrc/enum.py
dtrc/make.py
dtrc/poly.py
dtrc/trig.py
dtrc/util.py
dtrc-0.0.15.dist-info/LICENSE
dtrc-0.0.15.dist-info/METADATA
dtrc-0.0.15.dist-info/WHEEL
dtrc-0.0.15.dist-info/entry_points.txt
dtrc-0.0.15.dist-info/top_level.txt
dtrc-0.0.15.dist-info/RECORD
