Metadata-Version: 2.1
Name: dtrc
Version: 0.0.15
Summary: data torch
Home-page: https://github.com/dsm-72/dtrc
Author: dsm-72
Author-email: sumner.magruder@yale.edu
License: Apache Software License 2.0
Keywords: dtrc data pytorch torch trc
Classifier: Development Status :: 4 - Beta
Classifier: Intended Audience :: Developers
Classifier: Natural Language :: English
Classifier: Programming Language :: Python :: 3.11
Classifier: License :: OSI Approved :: Apache Software License
Requires-Python: >=3.11
License-File: LICENSE
Requires-Dist: asto
Requires-Dist: astr
Requires-Dist: atup
Requires-Dist: chck
Requires-Dist: dref
Requires-Dist: dtyp
Requires-Dist: etrc
Requires-Dist: lmsg
Requires-Dist: lull
Requires-Dist: nchr
Requires-Dist: nlit
Requires-Dist: pcts
Requires-Dist: quac
Requires-Dist: seeder
Requires-Dist: sigr
Requires-Dist: slcs
Requires-Dist: uscr
Requires-Dist: utrc
Requires-Dist: zipr
Provides-Extra: dev
Requires-Dist: numpy ; extra == 'dev'
Requires-Dist: pandas ; extra == 'dev'
Requires-Dist: matplotlib ; extra == 'dev'
Requires-Dist: torch ; extra == 'dev'
Requires-Dist: pytorch-lightning ; extra == 'dev'
Requires-Dist: torchvision ; extra == 'dev'
Requires-Dist: lightning ; extra == 'dev'
